jedi_xlsx/__init__.py
jedi_xlsx/xlsx.py
jedi_xlsx-0.1.2.dist-info/WHEEL
jedi_xlsx-0.1.2.dist-info/METADATA
jedi_xlsx-0.1.2.dist-info/RECORD
