Metadata-Version: 2.1
Name: jedi-xlsx
Version: 0.1.2
Summary: 
Author: JediHero
Author-email: hansen.rusty@gmail.com
Requires-Python: >=3.8,<4.0
Classifier: Programming Language :: Python :: 3
Classifier: Programming Language :: Python :: 3.8
Requires-Dist: pandas (>=1.1.2,<2.0.0)
Requires-Dist: toolz (>=0.11.1,<0.12.0)
Requires-Dist: xlrd[dev] (>=1.2.0,<2.0.0)
Requires-Dist: xlsxwriter (>=1.3.6,<2.0.0)
